financial_stochastic_processes/StochasticAssetPriceSimulator.py
financial_stochastic_processes/__init__.py
financial_stochastic_processes-0.1.6.dist-info/LICENSE.txt
financial_stochastic_processes-0.1.6.dist-info/METADATA
financial_stochastic_processes-0.1.6.dist-info/WHEEL
financial_stochastic_processes-0.1.6.dist-info/top_level.txt
financial_stochastic_processes-0.1.6.dist-info/RECORD
