Metadata-Version: 2.1
Name: financial_stochastic_processes
Version: 0.1.6
Summary: A package for simulating financial stochastic processes.
Home-page: https://github.com/MasonQ0813/FiancialStochasticProcesses
Author: Hao Quan & Ben Feng
Author-email: h5quan@uwaterloo.ca
Classifier: Programming Language :: Python :: 3
Classifier: License :: OSI Approved :: MIT License
Classifier: Operating System :: OS Independent
Requires-Python: >=3.6
License-File: LICENSE.txt
Requires-Dist: numpy
